ab_core/logging/__init__.py
ab_core/logging/config.py
ab_logging-0.1.3.dist-info/METADATA
ab_logging-0.1.3.dist-info/WHEEL
ab_logging-0.1.3.dist-info/licenses/LICENSE
ab_logging-0.1.3.dist-info/RECORD
