Metadata-Version: 2.4
Name: ab-logging
Version: 0.1.3
Summary: Standardized logging for auth broker services.
Author-email: Matt Coulter <mattcoul7@gmail.com>
License-File: LICENSE
Requires-Python: <4.0,>=3.12
Requires-Dist: pydantic>=2.11.10
Requires-Dist: rich>=14.1.0
